sels8s/__init__.py
sels8s/client.py
sels8s-1.0.7.dist-info/LICENSE
sels8s-1.0.7.dist-info/METADATA
sels8s-1.0.7.dist-info/WHEEL
sels8s-1.0.7.dist-info/top_level.txt
sels8s-1.0.7.dist-info/RECORD
