Metadata-Version: 2.1
Name: sels8s
Version: 1.0.7
Summary: SDK for python serverless functions
Home-page: https://github.com/selectel/serverless-python
Author-email: serov@selectel.ru
License: UNKNOWN
Platform: UNKNOWN
Requires-Dist: requests (==2.24.0)
Requires-Dist: keystoneauth1 (==3.17.1)
Requires-Dist: python-keystoneclient (==3.21.0)
